<?xml version="1.0" encoding="UTF-8"?>
<!DOCTYPE mapper PUBLIC "-//mybatis.org//DTD Mapper 3.0//EN" "http://mybatis.org/dtd/mybatis-3-mapper.dtd">
<mapper namespace="lt.vu.psk.mybatis.dao.DutiesRepresentativesMapper">
  <resultMap id="BaseResultMap" type="lt.vu.psk.mybatis.model.DutiesRepresentatives">
    <!--
      WARNING - @mbg.generated
      This element is automatically generated by MyBatis Generator, do not modify.
      This element was generated on Wed May 18 11:32:46 EEST 2022.
    -->
    <result column="REPRESENTATIVE_ID" jdbcType="INTEGER" property="representativeId" />
    <result column="DUTY_ID" jdbcType="INTEGER" property="dutyId" />
  </resultMap>
  <insert id="insert" parameterType="lt.vu.psk.mybatis.model.DutiesRepresentatives">
    <!--
      WARNING - @mbg.generated
      This element is automatically generated by MyBatis Generator, do not modify.
      This element was generated on Wed May 18 11:32:46 EEST 2022.
    -->
    insert into PUBLIC.DUTIES_REPRESENTATIVES (REPRESENTATIVE_ID, DUTY_ID)
    values (#{representativeId,jdbcType=INTEGER}, #{dutyId,jdbcType=INTEGER})
  </insert>
  <select id="selectAll" resultMap="BaseResultMap">
    <!--
      WARNING - @mbg.generated
      This element is automatically generated by MyBatis Generator, do not modify.
      This element was generated on Wed May 18 11:32:46 EEST 2022.
    -->
    select REPRESENTATIVE_ID, DUTY_ID
    from PUBLIC.DUTIES_REPRESENTATIVES
  </select>
  <select id="getResultCountByDutyAndRepresentativeId" resultType="INTEGER">
    SELECT count(*)
    FROM PUBLIC.DUTIES_REPRESENTATIVES dr
    WHERE dr.duty_id = #{dutyId, jdbcType=INTEGER} AND dr.representative_id = #{representativeId, jdbcType=INTEGER}
  </select>
</mapper>